pymongol/document.py
pymongol-0.0.2.dist-info/LICENSE
pymongol-0.0.2.dist-info/METADATA
pymongol-0.0.2.dist-info/WHEEL
pymongol-0.0.2.dist-info/top_level.txt
pymongol-0.0.2.dist-info/RECORD
