Metadata-Version: 2.1
Name: pymongol
Version: 0.0.2
Summary: A simple ORM for mongodb based on pymongo
Author-email: Amin Fazlali <amin@fazlali.net>
Project-URL: Homepage, https://github.com/fazlali/pymongol
Project-URL: Bug Tracker, https://github.com/fazlali/pymongol/issues
Classifier: Programming Language :: Python :: 3
Classifier: License :: OSI Approved :: MIT License
Classifier: Operating System :: OS Independent
Requires-Python: >=3.7
License-File: LICENSE
Requires-Dist: pymongo
Requires-Dist: inflect
